arpapy/__init__.py
arpapy/arpa.py
arpapy/const.py
arpapy/espeak.py
arpapy/excepts.py
arpapy/segment.py
arpapy/util.py
arpapy/model/__init__.py
arpapy/model/phoneme.py
arpapy/model/stress.py
arpapy/model/syllable.py
arpapy-0.0.3.dist-info/licenses/LICENSE
arpapy-0.0.3.dist-info/METADATA
arpapy-0.0.3.dist-info/WHEEL
arpapy-0.0.3.dist-info/top_level.txt
arpapy-0.0.3.dist-info/RECORD
