Metadata-Version: 2.4
Name: arpapy
Version: 0.0.3
Summary: Multilingual text/IPA to ARPAbet G2P for text2speech generation.
Author-email: Koke_Cacao <i@kokecacao.me>
Maintainer-email: Koke_Cacao <i@kokecacao.me>
License:                                  Apache License
Project-URL: Homepage, https://github.com/KokeCacao/arpapy
Project-URL: Documentation, https://github.com/KokeCacao/arpapy
Project-URL: Repository, https://github.com/KokeCacao/arpapy.git
Project-URL: Issues, https://github.com/KokeCacao/arpapy/issues
Project-URL: Bug Tracker, https://github.com/KokeCacao/arpapy/issues
Project-URL: Changelog, https://github.com/KokeCacao/arpapy/commits/master
Keywords: utility
Classifier: Development Status :: 4 - Beta
Classifier: Programming Language :: Python :: 3
Classifier: Programming Language :: Python :: 3.8
Classifier: Programming Language :: Python :: 3.9
Classifier: Programming Language :: Python :: 3.10
Classifier: Programming Language :: Python :: 3.11
Classifier: License :: OSI Approved :: Apache Software License
Classifier: Operating System :: OS Independent
Requires-Python: >=3.8
License-File: LICENSE
Requires-Dist: pykakasi
Dynamic: license-file
